[{"id":6310664798,"node_id":"LA_kwDOK4Lsvs8AAAABeCUaXg","url":"https://api.github.com/repos/skypesky666/public-demo/labels/bug","name":"bug","color":"d73a4a","default":true,"description":"Something isn't working"},{"id":6310664801,"node_id":"LA_kwDOK4Lsvs8AAAABeCUaYQ","url":"https://api.github.com/repos/skypesky666/public-demo/labels/documentation","name":"documentation","color":"0075ca","default":true,"description":"Improvements or additions to documentation"},{"id":6310664803,"node_id":"LA_kwDOK4Lsvs8AAAABeCUaYw","url":"https://api.github.com/repos/skypesky666/public-demo/labels/duplicate","name":"duplicate","color":"cfd3d7","default":true,"description":"This issue or pull request already exists"},{"id":6310664805,"node_id":"LA_kwDOK4Lsvs8AAAABeCUaZQ","url":"https://api.github.com/repos/skypesky666/public-demo/labels/enhancement","name":"enhancement","color":"a2eeef","default":true,"description":"New feature or request"},{"id":6310664808,"node_id":"LA_kwDOK4Lsvs8AAAABeCUaaA","url":"https://api.github.com/repos/skypesky666/public-demo/labels/good%20first%20issue","name":"good first issue","color":"7057ff","default":true,"description":"Good for newcomers"},{"id":6310664811,"node_id":"LA_kwDOK4Lsvs8AAAABeCUaaw","url":"https://api.github.com/repos/skypesky666/public-demo/labels/help%20wanted","name":"help wanted","color":"008672","default":true,"description":"Extra attention is needed"},{"id":6310664815,"node_id":"LA_kwDOK4Lsvs8AAAABeCUabw","url":"https://api.github.com/repos/skypesky666/public-demo/labels/invalid","name":"invalid","color":"e4e669","default":true,"description":"This doesn't seem right"},{"id":6310664817,"node_id":"LA_kwDOK4Lsvs8AAAABeCUacQ","url":"https://api.github.com/repos/skypesky666/public-demo/labels/question","name":"question","color":"d876e3","default":true,"description":"Further information is requested"},{"id":6310664819,"node_id":"LA_kwDOK4Lsvs8AAAABeCUacw","url":"https://api.github.com/repos/skypesky666/public-demo/labels/wontfix","name":"wontfix","color":"ffffff","default":true,"description":"This will not be worked on"}]
